pycontent_type/__init__.py
pycontent_type/py.typed
pycontent_type/query.py
pycontent_type/data/application.json
pycontent_type/data/audio.json
pycontent_type/data/font.json
pycontent_type/data/image.json
pycontent_type/data/message.json
pycontent_type/data/model.json
pycontent_type/data/multipart.json
pycontent_type/data/text.json
pycontent_type/data/video.json
pycontent_type-1.1.0.dist-info/METADATA
pycontent_type-1.1.0.dist-info/WHEEL
pycontent_type-1.1.0.dist-info/licenses/LICENSE
pycontent_type-1.1.0.dist-info/RECORD
