Metadata-Version: 2.1
Name: pycontent_type
Version: 1.1.0
Summary: Python library to access all Supported Content-Types/Media-Types
Project-URL: Homepage, https://github.com/yezz123/pycontent_type
Project-URL: Funding, https://github.com/sponsors/yezz123
Author-email: Yasser Tahiri <hello@yezz.me>
License-Expression: MIT
License-File: LICENSE
Keywords: Content-Type,MIME,MIME-Type,Media-Type
Classifier: Development Status :: 5 - Production/Stable
Classifier: Intended Audience :: Developers
Classifier: Intended Audience :: Information Technology
Classifier: License :: OSI Approved :: MIT License
Classifier: Operating System :: OS Independent
Classifier: Programming Language :: Python
Classifier: Programming Language :: Python :: 3
Classifier: Programming Language :: Python :: 3 :: Only
Classifier: Programming Language :: Python :: 3.7
Classifier: Programming Language :: Python :: 3.8
Classifier: Programming Language :: Python :: 3.9
Classifier: Programming Language :: Python :: 3.10
Classifier: Programming Language :: Python :: 3.11
Classifier: Topic :: Internet
Classifier: Topic :: Internet :: WWW/HTTP :: Session
Classifier: Topic :: Software Development :: Libraries :: Python Modules
Classifier: Typing :: Typed
Requires-Python: >=3.7
Requires-Dist: setuptools
Requires-Dist: typing-extensions<4.7.0,>=3.7.4
Provides-Extra: lint
Requires-Dist: mypy==1.3.0; extra == 'lint'
Requires-Dist: pre-commit==3.3.2; extra == 'lint'
Provides-Extra: test
Requires-Dist: httpx==0.24.1; extra == 'test'
Requires-Dist: pytest-asyncio==0.21.0; extra == 'test'
Requires-Dist: pytest-cov==4.1.0; extra == 'test'
Requires-Dist: pytest==7.3.1; extra == 'test'
Requires-Dist: requests==2.31.0; extra == 'test'
